chess/__init__.py
chess/bishop.py
chess/board.py
chess/castle_right.py
chess/color.py
chess/direction.py
chess/exceptions.py
chess/game.py
chess/king.py
chess/knight.py
chess/line.py
chess/move.py
chess/offset.py
chess/pawn.py
chess/piece.py
chess/piece_type.py
chess/position.py
chess/position_constants.py
chess/queen.py
chess/ray.py
chess/rect.py
chess/rook.py
chess/rules.py
chess/segment.py
chess/side.py
chess/size.py
56kyle_pychess-0.4.0.dist-info/LICENSE
56kyle_pychess-0.4.0.dist-info/WHEEL
56kyle_pychess-0.4.0.dist-info/METADATA
56kyle_pychess-0.4.0.dist-info/RECORD
