Metadata-Version: 2.1
Name: 56kyle-pychess
Version: 0.4.0
Summary: A python chess engine
Home-page: https://github.com/56kyle/pychess
License: MIT
Keywords: chess,python,engine
Author: kyle
Author-email: 56kyleoliver@gmail.com
Requires-Python: >=3.10,<4.0
Classifier: Development Status :: 3 - Alpha
Classifier: Intended Audience :: Developers
Classifier: License :: OSI Approved :: MIT License
Classifier: Programming Language :: Python :: 3
Classifier: Programming Language :: Python :: 3.10
Classifier: Programming Language :: Python :: 3.11
Classifier: Topic :: Games/Entertainment :: Board Games
Classifier: Topic :: Software Development :: Libraries :: Python Modules
Project-URL: Repository, https://github.com/56kyle/pychess
